stSMILE/__init__.py
stSMILE/analysis.py
stSMILE/model.py
stSMILE/utils.py
stSMILE-1.0.0.dist-info/LICENSE
stSMILE-1.0.0.dist-info/METADATA
stSMILE-1.0.0.dist-info/WHEEL
stSMILE-1.0.0.dist-info/top_level.txt
stSMILE-1.0.0.dist-info/RECORD
