Metadata-Version: 2.1
Name: stSMILE
Version: 1.0.0
Summary: Multiscale dissection of spatial heterogeneity by integrating multi-slice spatial and single-cell transcriptomics
Home-page: https://github.com/lhzhanglabtools/SMILE
Author: Lihua Zhang
Author-email: zhanglh@whu.edu.cn
License: MIT
License-File: LICENSE
Requires-Dist: requests
